{
  "name": "Global Patriot Newspapers online",
  "slug": "global-patriot-newspapers-online",
  "summary": {
    "total_posts": 26,
    "total_engagement": 242821,
    "total_followers": 885,
    "platforms_active": 2,
    "engagement_rate": 9339.27,
    "last_updated": "2026-01-08T23:13:30.201686"
  },
  "platform_breakdown": {
    "tiktok": {
      "posts": 26,
      "posts_pct": 100.0,
      "engagement": 242821,
      "engagement_pct": 100.0
    },
    "twitter": {
      "posts": 0,
      "posts_pct": 0.0,
      "engagement": 0,
      "engagement_pct": 0.0
    }
  },
  "platforms": {
    "tiktok": {
      "posts": 26,
      "engagement": 242821,
      "views": 516800,
      "followers": 0,
      "engagement_rate": 9339.27,
      "top_posts": [
        {
          "id": "7575664444659813662",
          "url": "https://www.tiktok.com/@globalpatriot/video/7575664444659813662",
          "text": "Fafo",
          "date": "2025-11-22T14:27:33",
          "engagement": {
            "likes": 9482,
            "comments": 57,
            "shares": 10200,
            "views": 13800,
            "total": 19739
          },
          "thumbnail": "https://p16-common-sign.tiktokcdn-us.com/tos-useast8-p-0068-tx2/oYEhAIDB9Qp6FJ9nJVfBRtMBY0KeViEaAEEKGQ~tplv-tiktokx-origin.image?dr=9636&x-expires=1768104000&x-signature=fBX%2B6hfk6R%2FKEuiiZxZhCeah%2FVc%3D&t=4d5b0474&ps=13740610&shp=81f88b70&shcp=43f4a2f9&idc=useast5"
        },
        {
          "id": "7573162558828383519",
          "url": "https://www.tiktok.com/@globalpatriot/video/7573162558828383519",
          "text": "My name is Richard Cannon. Many people know me as Global Patriot, but...",
          "date": "2025-11-15T20:38:49",
          "engagement": {
            "likes": 12700,
            "comments": 133,
            "shares": 5919,
            "views": 27000,
            "total": 18752
          },
          "thumbnail": "https://p16-common-sign.tiktokcdn-us.com/tos-useast8-p-0068-tx2/o8SOqfl8HCxgoALjLIYgzSeKrMIKAcexn3HGIE~tplv-tiktokx-origin.image?dr=9636&x-expires=1768104000&x-signature=6hJ2Ld6Cf90Zd8XKqRxe2UIX5Oc%3D&t=4d5b0474&ps=13740610&shp=81f88b70&shcp=43f4a2f9&idc=useast5"
        },
        {
          "id": "7574987784834927902",
          "url": "https://www.tiktok.com/@globalpatriot/video/7574987784834927902",
          "text": "TikTok video #7574987784834927902",
          "date": "2025-11-20T18:41:39",
          "engagement": {
            "likes": 9464,
            "comments": 37,
            "shares": 7401,
            "views": 14700,
            "total": 16902
          },
          "thumbnail": "https://p16-common-sign.tiktokcdn-us.com/tos-useast8-p-0068-tx2/oc1zQAFUVRVHOt4fEBDAQNHkRbpAwBYEL8EZf6~tplv-tiktokx-origin.image?dr=9636&x-expires=1768104000&x-signature=ZHFHi4%2BDm64Pf5wHI9dVf2d471g%3D&t=4d5b0474&ps=13740610&shp=81f88b70&shcp=43f4a2f9&idc=useast5"
        }
      ],
      "frequency": {
        "posts_per_day": 0.34,
        "posts_per_week": 2.38,
        "date_range_days": 73,
        "first_post": "2025-10-26T08:42:24",
        "last_post": "2026-01-07T22:59:00"
      },
      "time_series": [
        {
          "date": "2025-10-20",
          "posts": 1,
          "engagement": 9540
        },
        {
          "date": "2025-10-27",
          "posts": 2,
          "engagement": 24664
        },
        {
          "date": "2025-11-03",
          "posts": 5,
          "engagement": 60916
        },
        {
          "date": "2025-11-10",
          "posts": 1,
          "engagement": 18752
        },
        {
          "date": "2025-11-17",
          "posts": 3,
          "engagement": 52853
        },
        {
          "date": "2025-11-24",
          "posts": 1,
          "engagement": 13779
        },
        {
          "date": "2025-12-08",
          "posts": 3,
          "engagement": 20092
        },
        {
          "date": "2025-12-15",
          "posts": 1,
          "engagement": 5345
        },
        {
          "date": "2025-12-22",
          "posts": 4,
          "engagement": 23080
        },
        {
          "date": "2025-12-29",
          "posts": 1,
          "engagement": 6817
        },
        {
          "date": "2026-01-05",
          "posts": 3,
          "engagement": 6983
        }
      ],
      "content_types": {
        "video": {
          "count": 26,
          "engagement": 242821,
          "percentage": 100.0
        }
      }
    },
    "twitter": {
      "posts": 0,
      "engagement": 0,
      "views": 0,
      "followers": 885,
      "engagement_rate": 0.0,
      "top_posts": [],
      "frequency": {
        "posts_per_day": 0,
        "posts_per_week": 0,
        "date_range_days": 0,
        "first_post": null,
        "last_post": null
      },
      "time_series": [],
      "content_types": {}
    }
  },
  "top_posts": [
    {
      "id": "7575664444659813662",
      "url": "https://www.tiktok.com/@globalpatriot/video/7575664444659813662",
      "text": "Fafo",
      "date": "2025-11-22T14:27:33",
      "engagement": {
        "likes": 9482,
        "comments": 57,
        "shares": 10200,
        "views": 13800,
        "total": 19739
      },
      "thumbnail": "https://p16-common-sign.tiktokcdn-us.com/tos-useast8-p-0068-tx2/oYEhAIDB9Qp6FJ9nJVfBRtMBY0KeViEaAEEKGQ~tplv-tiktokx-origin.image?dr=9636&x-expires=1768104000&x-signature=fBX%2B6hfk6R%2FKEuiiZxZhCeah%2FVc%3D&t=4d5b0474&ps=13740610&shp=81f88b70&shcp=43f4a2f9&idc=useast5"
    },
    {
      "id": "7573162558828383519",
      "url": "https://www.tiktok.com/@globalpatriot/video/7573162558828383519",
      "text": "My name is Richard Cannon. Many people know me as Global Patriot, but...",
      "date": "2025-11-15T20:38:49",
      "engagement": {
        "likes": 12700,
        "comments": 133,
        "shares": 5919,
        "views": 27000,
        "total": 18752
      },
      "thumbnail": "https://p16-common-sign.tiktokcdn-us.com/tos-useast8-p-0068-tx2/o8SOqfl8HCxgoALjLIYgzSeKrMIKAcexn3HGIE~tplv-tiktokx-origin.image?dr=9636&x-expires=1768104000&x-signature=6hJ2Ld6Cf90Zd8XKqRxe2UIX5Oc%3D&t=4d5b0474&ps=13740610&shp=81f88b70&shcp=43f4a2f9&idc=useast5"
    },
    {
      "id": "7574987784834927902",
      "url": "https://www.tiktok.com/@globalpatriot/video/7574987784834927902",
      "text": "TikTok video #7574987784834927902",
      "date": "2025-11-20T18:41:39",
      "engagement": {
        "likes": 9464,
        "comments": 37,
        "shares": 7401,
        "views": 14700,
        "total": 16902
      },
      "thumbnail": "https://p16-common-sign.tiktokcdn-us.com/tos-useast8-p-0068-tx2/oc1zQAFUVRVHOt4fEBDAQNHkRbpAwBYEL8EZf6~tplv-tiktokx-origin.image?dr=9636&x-expires=1768104000&x-signature=ZHFHi4%2BDm64Pf5wHI9dVf2d471g%3D&t=4d5b0474&ps=13740610&shp=81f88b70&shcp=43f4a2f9&idc=useast5"
    },
    {
      "id": "7575714926388432158",
      "url": "https://www.tiktok.com/@globalpatriot/video/7575714926388432158",
      "text": "TikTok video #7575714926388432158",
      "date": "2025-11-22T17:43:21",
      "engagement": {
        "likes": 6469,
        "comments": 59,
        "shares": 9684,
        "views": 15100,
        "total": 16212
      },
      "thumbnail": "https://p16-common-sign.tiktokcdn-us.com/tos-useast8-p-0068-tx2/oUQEQBInjsFRAYMSFXBP8VeeMFwIFQzAqeLVCK~tplv-tiktokx-origin.image?dr=9636&x-expires=1768104000&x-signature=PJGrklwnJu%2FEiPSeJIVOnUPOW0s%3D&t=4d5b0474&ps=13740610&shp=81f88b70&shcp=43f4a2f9&idc=useast5"
    },
    {
      "id": "7569783029212744990",
      "url": "https://www.tiktok.com/@globalpatriot/video/7569783029212744990",
      "text": "I pass this photo on my wall every day dozens of times and never miss...",
      "date": "2025-11-06T18:04:29",
      "engagement": {
        "likes": 10900,
        "comments": 107,
        "shares": 3616,
        "views": 39200,
        "total": 14623
      },
      "thumbnail": "https://p16-common-sign.tiktokcdn-us.com/tos-useast8-p-0068-tx2/ok80hABBIiAi5A4afCAAIAJi8qNM3TvFab5IqR~tplv-tiktokx-origin.image?dr=9636&x-expires=1768104000&x-signature=W6dAPV1yhNihKoT3sABowfW5bUo%3D&t=4d5b0474&ps=13740610&shp=81f88b70&shcp=43f4a2f9&idc=useast5"
    }
  ],
  "overall_frequency": {
    "posts_per_day": 0.34,
    "posts_per_week": 2.38,
    "date_range_days": 73,
    "first_post": "2025-10-26T08:42:24",
    "last_post": "2026-01-07T22:59:00"
  },
  "time_series": [
    {
      "date": "2025-10-20",
      "posts": 1,
      "engagement": 9540
    },
    {
      "date": "2025-10-27",
      "posts": 2,
      "engagement": 24664
    },
    {
      "date": "2025-11-03",
      "posts": 5,
      "engagement": 60916
    },
    {
      "date": "2025-11-10",
      "posts": 1,
      "engagement": 18752
    },
    {
      "date": "2025-11-17",
      "posts": 3,
      "engagement": 52853
    },
    {
      "date": "2025-11-24",
      "posts": 1,
      "engagement": 13779
    },
    {
      "date": "2025-12-08",
      "posts": 3,
      "engagement": 20092
    },
    {
      "date": "2025-12-15",
      "posts": 1,
      "engagement": 5345
    },
    {
      "date": "2025-12-22",
      "posts": 4,
      "engagement": 23080
    },
    {
      "date": "2025-12-29",
      "posts": 1,
      "engagement": 6817
    },
    {
      "date": "2026-01-05",
      "posts": 3,
      "engagement": 6983
    }
  ],
  "grantInfo": {
    "totalFunding": 3300,
    "formattedFunding": "$3K",
    "years": [
      "2025"
    ],
    "status": "active",
    "county": "North Jersey",
    "city": "Paterson",
    "focusArea": "Journalism pipeline",
    "grantCount": 1,
    "hasMultipleGrants": false,
    "grants": [
      {
        "id": 1,
        "years": [
          "2025"
        ],
        "amount": 3300,
        "formattedAmount": "$3K",
        "description": "To support the placement of a student intern through the Statewide Paid Internship Program.",
        "focusArea": "Journalism pipeline",
        "status": "active"
      }
    ]
  },
  "website": "https://www.globalpatriotnews.com",
  "social": {
    "twitter": "https://x.com/globalpatriot",
    "tiktok": "https://tiktok.com/@globalpatriot"
  }
}